tfl/__init__.py
tfl/__main__.py
tfl/api/__init__.py
tfl/api/bike_point.py
tfl/api/factory.py
tfl/api/line/__init__.py
tfl/api/line/meta/__init__.py
tfl/api/presentation/__init__.py
tfl/api/presentation/entities/__init__.py
tfl/api/presentation/entities/additional_properties.py
tfl/api/presentation/entities/disruption.py
tfl/api/presentation/entities/line.py
tfl/api/presentation/entities/mode.py
tfl/api/presentation/entities/place.py
tfl/api/presentation/entities/places_response.py
tfl/api/presentation/entities/status_severity.py
tfl/cli/__init__.py
tfl/cli/cycles.py
mind_the_gap-2.1.2.dist-info/METADATA
mind_the_gap-2.1.2.dist-info/WHEEL
mind_the_gap-2.1.2.dist-info/entry_points.txt
mind_the_gap-2.1.2.dist-info/RECORD
